sqlitedave_package/.schemawiz_config3
sqlitedave_package/__init__.py
sqlitedave_package/a.csv
sqlitedave_package/complexdata.csv
sqlitedave_package/execute.py
sqlitedave_package/postgres_data.tsv
sqlitedave_package/query.py
sqlitedave_package/select.sql
sqlitedave_package/sqlitedave.py
sqlitedave_package/testcase1.csv
sqlitedave_package/that_db
sqlitedave_package/this_db
sqlitedave_package/z.testcase1.ddl
sqlitedave_package-2.0.1.dist-info/METADATA
sqlitedave_package-2.0.1.dist-info/WHEEL
sqlitedave_package-2.0.1.dist-info/licenses/LICENSE
sqlitedave_package-2.0.1.dist-info/RECORD
