Metadata-Version: 2.1
Name: sqlitedave_package
Version: 2.0.1
Summary: A wrapper for simplified sqlite usage using sqlite3.
Project-URL: Homepage, https://github.com/daveskura/sqlitedave
Project-URL: Author Linkedin, https://www.linkedin.com/in/2166883
Author-email: Dave Skura <dskura@gmail.com>
License-File: LICENSE
Classifier: License :: OSI Approved :: MIT License
Classifier: Operating System :: OS Independent
Classifier: Programming Language :: Python :: 3
Requires-Python: >=3.7
Requires-Dist: garbledave-package>=1.0.0
